[
    {
        "seller": "Xilef",
        "sellerid": "852882606629847050",
        "buyer": "Xilef",
        "buyerid": "852882606629847050",
        "price": 0
    },
    {
        "seller": "Xilef",
        "sellerid": "852882606629847050",
        "buyer": "Felix44",
        "buyerid": "621307633718132746",
        "price": 100
    },
    {
        "seller": "Xilef",
        "sellerid": "852882606629847050",
        "buyer": "Felix44",
        "buyerid": "621307633718132746",
        "price": 100
    },
    {
        "seller": "Xilef",
        "sellerid": "852882606629847050",
        "buyer": "Felix44",
        "buyerid": "621307633718132746",
        "price": 100
    },
    {
        "seller": "Xilef",
        "sellerid": "852882606629847050",
        "buyer": "Felix44",
        "buyerid": "621307633718132746",
        "price": 100
    },
    {
        "seller": "Xilef",
        "sellerid": "852882606629847050",
        "buyer": "Felix44",
        "buyerid": "621307633718132746",
        "price": 100
    },
    {
        "seller": "Xilef",
        "sellerid": "852882606629847050",
        "buyer": "Felix44",
        "buyerid": "621307633718132746",
        "price": 100
    },
    {
        "seller": "Xilef",
        "sellerid": "852882606629847050",
        "buyer": "Felix44",
        "buyerid": "621307633718132746",
        "price": 100
    },
    {
        "seller": "Xilef",
        "sellerid": "852882606629847050",
        "buyer": "Felix44",
        "buyerid": "621307633718132746",
        "price": 100
    },
    {
        "seller": "Xilef",
        "sellerid": "852882606629847050",
        "buyer": "Felix44",
        "buyerid": "621307633718132746",
        "price": 100
    },
    {
        "seller": "Xilef",
        "sellerid": "852882606629847050",
        "buyer": "Felix44",
        "buyerid": "621307633718132746",
        "price": 100
    },
    {
        "seller": "Felix44",
        "sellerid": "621307633718132746",
        "buyer": "Dark_Brick",
        "buyerid": "484682433925611542",
        "price": 4206942069
    },
    {
        "seller": "Felix44",
        "sellerid": "621307633718132746",
        "buyer": "Dark_Brick",
        "buyerid": "484682433925611542",
        "price": 420420420
    }
]